mkdocs_jconfig/__init__.py
mkdocs_jconfig/plugin.py
mkdocs_jconfig_plugin-0.1.3.dist-info/METADATA
mkdocs_jconfig_plugin-0.1.3.dist-info/WHEEL
mkdocs_jconfig_plugin-0.1.3.dist-info/entry_points.txt
mkdocs_jconfig_plugin-0.1.3.dist-info/RECORD
